{
  "annotations": {
    "list": []
  },
  "editable": true,
  "fiscalYearStartMonth": 0,
  "graphTooltip": 1,
  "id": null,
  "links": [],
  "liveNow": false,
  "panels": [
    {
      "collapsed": false,
      "gridPos": { "h": 1, "w": 24, "x": 0, "y": 0 },
      "id": 1,
      "panels": [],
      "title": "🚀 Overview",
      "type": "row"
    },
    {
      "datasource": { "type": "prometheus", "uid": "prometheus" },
      "fieldConfig": {
        "defaults": {
          "color": { "mode": "thresholds" },
          "mappings": [
            { "options": { "0": { "color": "red", "text": "DOWN" }, "1": { "color": "green", "text": "UP" } }, "type": "value" }
          ],
          "thresholds": {
            "mode": "absolute",
            "steps": [
              { "color": "red", "value": null },
              { "color": "green", "value": 1 }
            ]
          }
        }
      },
      "gridPos": { "h": 4, "w": 4, "x": 0, "y": 1 },
      "id": 2,
      "options": {
        "colorMode": "value",
        "graphMode": "none",
        "justifyMode": "auto",
        "orientation": "auto",
        "reduceOptions": { "calcs": ["lastNotNull"], "fields": "", "values": false },
        "textMode": "value"
      },
      "title": "API Status",
      "type": "stat",
      "targets": [
        { "expr": "up{job=\"rick-morty-api\"}", "refId": "A" }
      ]
    },
    {
      "datasource": { "type": "prometheus", "uid": "prometheus" },
      "fieldConfig": {
        "defaults": {
          "color": { "mode": "palette-classic" },
          "unit": "reqps"
        }
      },
      "gridPos": { "h": 4, "w": 5, "x": 4, "y": 1 },
      "id": 3,
      "options": {
        "colorMode": "value",
        "graphMode": "area",
        "justifyMode": "auto",
        "orientation": "auto",
        "reduceOptions": { "calcs": ["lastNotNull"], "fields": "", "values": false }
      },
      "title": "Request Rate",
      "type": "stat",
      "targets": [
        { "expr": "sum(rate(flask_http_request_total[5m]))", "refId": "A" }
      ]
    },
    {
      "datasource": { "type": "prometheus", "uid": "prometheus" },
      "fieldConfig": {
        "defaults": {
          "color": { "mode": "thresholds" },
          "unit": "s",
          "thresholds": {
            "mode": "absolute",
            "steps": [
              { "color": "green", "value": null },
              { "color": "yellow", "value": 0.5 },
              { "color": "red", "value": 1 }
            ]
          }
        }
      },
      "gridPos": { "h": 4, "w": 5, "x": 9, "y": 1 },
      "id": 4,
      "options": {
        "colorMode": "value",
        "graphMode": "area",
        "justifyMode": "auto",
        "orientation": "auto",
        "reduceOptions": { "calcs": ["mean"], "fields": "", "values": false }
      },
      "title": "Avg Response Time",
      "type": "stat",
      "targets": [
        { "expr": "histogram_quantile(0.50, sum(rate(flask_http_request_duration_seconds_bucket[5m])) by (le))", "refId": "A" }
      ]
    },
    {
      "datasource": { "type": "prometheus", "uid": "prometheus" },
      "fieldConfig": {
        "defaults": {
          "color": { "mode": "thresholds" },
          "unit": "percentunit",
          "thresholds": {
            "mode": "absolute",
            "steps": [
              { "color": "green", "value": null },
              { "color": "yellow", "value": 0.01 },
              { "color": "red", "value": 0.05 }
            ]
          }
        }
      },
      "gridPos": { "h": 4, "w": 5, "x": 14, "y": 1 },
      "id": 5,
      "options": {
        "colorMode": "value",
        "graphMode": "none",
        "justifyMode": "auto",
        "orientation": "auto",
        "reduceOptions": { "calcs": ["lastNotNull"], "fields": "", "values": false }
      },
      "title": "Error Rate",
      "type": "stat",
      "targets": [
        { "expr": "sum(rate(flask_http_request_total{status=~\"5..\"}[5m])) / sum(rate(flask_http_request_total[5m])) or vector(0)", "refId": "A" }
      ]
    },
    {
      "datasource": { "type": "prometheus", "uid": "prometheus" },
      "fieldConfig": {
        "defaults": {
          "color": { "mode": "palette-classic" },
          "unit": "short"
        }
      },
      "gridPos": { "h": 4, "w": 5, "x": 19, "y": 1 },
      "id": 6,
      "options": {
        "colorMode": "value",
        "graphMode": "area",
        "justifyMode": "auto",
        "orientation": "auto",
        "reduceOptions": { "calcs": ["lastNotNull"], "fields": "", "values": false }
      },
      "title": "Total Requests",
      "type": "stat",
      "targets": [
        { "expr": "sum(flask_http_request_total)", "refId": "A" }
      ]
    },
    {
      "collapsed": false,
      "gridPos": { "h": 1, "w": 24, "x": 0, "y": 5 },
      "id": 7,
      "panels": [],
      "title": "📊 Request Metrics",
      "type": "row"
    },
    {
      "datasource": { "type": "prometheus", "uid": "prometheus" },
      "fieldConfig": {
        "defaults": {
          "color": { "mode": "palette-classic" },
          "custom": {
            "axisCenteredZero": false,
            "axisColorMode": "text",
            "axisLabel": "",
            "axisPlacement": "auto",
            "barAlignment": 0,
            "drawStyle": "line",
            "fillOpacity": 20,
            "gradientMode": "none",
            "lineInterpolation": "smooth",
            "lineWidth": 2,
            "pointSize": 5,
            "scaleDistribution": { "type": "linear" },
            "showPoints": "auto",
            "spanNulls": false,
            "stacking": { "group": "A", "mode": "none" },
            "thresholdsStyle": { "mode": "off" }
          },
          "unit": "reqps"
        }
      },
      "gridPos": { "h": 8, "w": 12, "x": 0, "y": 6 },
      "id": 8,
      "options": {
        "legend": { "calcs": ["mean", "max"], "displayMode": "table", "placement": "bottom", "showLegend": true },
        "tooltip": { "mode": "multi", "sort": "desc" }
      },
      "title": "Request Rate by Endpoint",
      "type": "timeseries",
      "targets": [
        { "expr": "sum(rate(flask_http_request_total[5m])) by (endpoint)", "legendFormat": "{{endpoint}}", "refId": "A" }
      ]
    },
    {
      "datasource": { "type": "prometheus", "uid": "prometheus" },
      "fieldConfig": {
        "defaults": {
          "color": { "mode": "palette-classic" },
          "custom": {
            "axisCenteredZero": false,
            "axisColorMode": "text",
            "drawStyle": "line",
            "fillOpacity": 10,
            "lineInterpolation": "smooth",
            "lineWidth": 2
          },
          "unit": "s"
        }
      },
      "gridPos": { "h": 8, "w": 12, "x": 12, "y": 6 },
      "id": 9,
      "options": {
        "legend": { "calcs": ["mean", "max"], "displayMode": "table", "placement": "bottom", "showLegend": true },
        "tooltip": { "mode": "multi", "sort": "desc" }
      },
      "title": "Response Time Percentiles",
      "type": "timeseries",
      "targets": [
        { "expr": "histogram_quantile(0.50, sum(rate(flask_http_request_duration_seconds_bucket[5m])) by (le))", "legendFormat": "p50", "refId": "A" },
        { "expr": "histogram_quantile(0.95, sum(rate(flask_http_request_duration_seconds_bucket[5m])) by (le))", "legendFormat": "p95", "refId": "B" },
        { "expr": "histogram_quantile(0.99, sum(rate(flask_http_request_duration_seconds_bucket[5m])) by (le))", "legendFormat": "p99", "refId": "C" }
      ]
    },
    {
      "collapsed": false,
      "gridPos": { "h": 1, "w": 24, "x": 0, "y": 14 },
      "id": 10,
      "panels": [],
      "title": "📈 HTTP Status Codes",
      "type": "row"
    },
    {
      "datasource": { "type": "prometheus", "uid": "prometheus" },
      "fieldConfig": {
        "defaults": {
          "color": { "mode": "palette-classic" },
          "custom": {
            "axisCenteredZero": false,
            "axisColorMode": "text",
            "drawStyle": "bars",
            "fillOpacity": 80,
            "lineWidth": 1,
            "stacking": { "group": "A", "mode": "normal" }
          },
          "unit": "short"
        }
      },
      "gridPos": { "h": 8, "w": 12, "x": 0, "y": 15 },
      "id": 11,
      "options": {
        "legend": { "calcs": ["sum"], "displayMode": "table", "placement": "right", "showLegend": true },
        "tooltip": { "mode": "multi", "sort": "desc" }
      },
      "title": "HTTP Status Codes Over Time",
      "type": "timeseries",
      "targets": [
        { "expr": "sum(increase(flask_http_request_total[1m])) by (status)", "legendFormat": "{{status}}", "refId": "A" }
      ]
    },
    {
      "datasource": { "type": "prometheus", "uid": "prometheus" },
      "fieldConfig": {
        "defaults": {
          "color": { "mode": "palette-classic" },
          "mappings": [],
          "unit": "short"
        },
        "overrides": [
          { "matcher": { "id": "byName", "options": "200" }, "properties": [{ "id": "color", "value": { "fixedColor": "green", "mode": "fixed" } }] },
          { "matcher": { "id": "byName", "options": "500" }, "properties": [{ "id": "color", "value": { "fixedColor": "red", "mode": "fixed" } }] },
          { "matcher": { "id": "byName", "options": "404" }, "properties": [{ "id": "color", "value": { "fixedColor": "yellow", "mode": "fixed" } }] }
        ]
      },
      "gridPos": { "h": 8, "w": 6, "x": 12, "y": 15 },
      "id": 12,
      "options": {
        "displayLabels": ["percent", "name"],
        "legend": { "displayMode": "table", "placement": "right", "showLegend": true },
        "pieType": "donut",
        "reduceOptions": { "calcs": ["sum"], "fields": "", "values": false },
        "tooltip": { "mode": "single", "sort": "none" }
      },
      "title": "Status Code Distribution",
      "type": "piechart",
      "targets": [
        { "expr": "sum(flask_http_request_total) by (status)", "legendFormat": "{{status}}", "refId": "A" }
      ]
    },
    {
      "datasource": { "type": "prometheus", "uid": "prometheus" },
      "fieldConfig": {
        "defaults": {
          "color": { "mode": "palette-classic" },
          "custom": { "align": "auto", "cellOptions": { "type": "auto" }, "inspect": false },
          "mappings": [],
          "unit": "short"
        },
        "overrides": [
          { "matcher": { "id": "byName", "options": "Count" }, "properties": [{ "id": "custom.cellOptions", "value": { "mode": "gradient", "type": "gauge" } }] }
        ]
      },
      "gridPos": { "h": 8, "w": 6, "x": 18, "y": 15 },
      "id": 13,
      "options": { "showHeader": true, "sortBy": [] },
      "title": "Requests by Endpoint",
      "type": "table",
      "targets": [
        { "expr": "sum(flask_http_request_total) by (endpoint)", "format": "table", "instant": true, "refId": "A" }
      ],
      "transformations": [
        { "id": "organize", "options": { "excludeByName": { "Time": true }, "renameByName": { "Value": "Count", "endpoint": "Endpoint" } } }
      ]
    }
  ],
  "refresh": "10s",
  "schemaVersion": 38,
  "style": "dark",
  "tags": ["rick-morty", "api", "flask", "prometheus"],
  "templating": { "list": [] },
  "time": { "from": "now-1h", "to": "now" },
  "timepicker": {},
  "timezone": "",
  "title": "🧪 Rick & Morty API Dashboard",
  "uid": "rick-morty-api",
  "version": 1,
  "weekStart": ""
}
